smartup/__init__.py
smartup/client.py
smartup/smartdance/__init__.py
smartup/smartdance/dance.py
smartup-0.0.3.dist-info/METADATA
smartup-0.0.3.dist-info/WHEEL
smartup-0.0.3.dist-info/top_level.txt
smartup-0.0.3.dist-info/RECORD
