Metadata-Version: 2.1
Name: smartup
Version: 0.0.3
Summary: A Python package for interacting with the SmartUp API and Platform.
Author: Marcelo Arias
Author-email: marcelo@smartup.lat
Classifier: Development Status :: 3 - Alpha
Classifier: Intended Audience :: Developers
Classifier: License :: OSI Approved :: MIT License
Classifier: Programming Language :: Python :: 3.6
Classifier: Programming Language :: Python :: 3.7
Classifier: Programming Language :: Python :: 3.8
Classifier: Programming Language :: Python :: 3.9
